stanza_batch/__init__.py
stanza_batch/version.py
stanza_batch-0.2.2.dist-info/LICENSE
stanza_batch-0.2.2.dist-info/METADATA
stanza_batch-0.2.2.dist-info/WHEEL
stanza_batch-0.2.2.dist-info/top_level.txt
stanza_batch-0.2.2.dist-info/RECORD
