Metadata-Version: 2.1
Name: stanza-batch
Version: 0.2.2
Summary: A batching utility for Stanza
Home-page: https://github.com/apmoore1/stanza-batch
Author: Andrew Moore
Author-email: andrew.p.moore94@gmail.com
License: Apache License 2.0
Keywords: natural-language-processing nlp natural-language-understanding stanford-nlp deep-learning
Platform: UNKNOWN
Classifier: Development Status :: 5 - Production/Stable
Classifier: Programming Language :: Python :: 3.6
Classifier: Programming Language :: Python :: 3.7
Classifier: Programming Language :: Python :: 3.8
Requires-Python: >=3.6.1
Requires-Dist: stanza (<=1.2.0,>=1.1.1)
